{"meta":{"name":"COSTA RICA","id":"Deluxeprime28","type":"channel","posterShape":"landscape","videos":[{"id":"Deluxeprimestream_28_0","title":"FUTV"},{"id":"Deluxeprimestream_28_1","title":"REPRETEL 11"},{"id":"Deluxeprimestream_28_2","title":"REPRETEL 4"},{"id":"Deluxeprimestream_28_3","title":"REPRETEL 6"},{"id":"Deluxeprimestream_28_4","title":"TD+"},{"id":"Deluxeprimestream_28_5","title":"Telemas"},{"id":"Deluxeprimestream_28_6","title":"TELETICA 7"},{"id":"Deluxeprimestream_28_7","title":"TeleUno"},{"id":"Deluxeprimestream_28_8","title":"TIGO SPORTS"}]}}